build/lib/pylon/__init__.py
build/lib/pylon/router.py
build/lib/pylon/server.py
pylon/__init__.py
pylon/router.py
pylon/server.py
pylon_web-0.1.0.dist-info/METADATA
pylon_web-0.1.0.dist-info/WHEEL
pylon_web-0.1.0.dist-info/top_level.txt
pylon_web-0.1.0.dist-info/RECORD
